CONTRIBUTING.rst
HISTORY.rst
LICENSE
MANIFEST.in
README.md
resources.qrc
setup.cfg
setup.py
./labelDetection.py
./resources.py
EfficientDet/__init__.py
EfficientDet/efficientnet.py
EfficientDet/inference.py
EfficientDet/initializers.py
EfficientDet/keras_.py
EfficientDet/layers.py
EfficientDet/losses.py
EfficientDet/model.py
EfficientDet/tfkeras.py
EfficientDet/train.py
EfficientDet/augmentor/__init__.py
EfficientDet/augmentor/color.py
EfficientDet/augmentor/misc.py
EfficientDet/augmentor/transform.py
EfficientDet/eval/__init__.py
EfficientDet/eval/coco.py
EfficientDet/eval/common.py
EfficientDet/eval/pascal.py
EfficientDet/generators/__init__.py
EfficientDet/generators/coco.py
EfficientDet/generators/common.py
EfficientDet/generators/csv_.py
EfficientDet/generators/pascal.py
EfficientDet/utils/__init__.py
EfficientDet/utils/anchors.py
EfficientDet/utils/colors.py
EfficientDet/utils/compute_overlap.py
EfficientDet/utils/image.py
EfficientDet/utils/transform.py
EfficientDet/utils/visualization.py
FSAF/callbacks.py
FSAF/configure.py
FSAF/fsaf_layers.py
FSAF/inference.py
FSAF/initializers.py
FSAF/layers.py
FSAF/losses.py
FSAF/setup.py
FSAF/train.py
FSAF/util_graphs.py
FSAF/augmentor/__init__.py
FSAF/augmentor/color.py
FSAF/augmentor/misc.py
FSAF/augmentor/transform.py
FSAF/generators/__init__.py
FSAF/generators/coco_generator.py
FSAF/generators/csv_generator.py
FSAF/generators/generator.py
FSAF/generators/voc_generator.py
FSAF/models/__init__.py
FSAF/models/densenet.py
FSAF/models/mobilenet.py
FSAF/models/resnet.py
FSAF/models/retinanet.py
FSAF/models/vgg.py
FSAF/utils/__init__.py
FSAF/utils/anchors.py
FSAF/utils/coco_eval.py
FSAF/utils/colors.py
FSAF/utils/compute_overlap.py
FSAF/utils/config.py
FSAF/utils/eval.py
FSAF/utils/image.py
FSAF/utils/keras_version.py
FSAF/utils/model.py
FSAF/utils/transform.py
FSAF/utils/visualization.py
FSAF/yolo/__init__.py
FSAF/yolo/config.py
FSAF/yolo/fsaf_layers.py
FSAF/yolo/inference.py
FSAF/yolo/model.py
FSAF/yolo/train.py
labelDetection.egg-info/PKG-INFO
labelDetection.egg-info/SOURCES.txt
labelDetection.egg-info/dependency_links.txt
labelDetection.egg-info/entry_points.txt
labelDetection.egg-info/not-zip-safe
labelDetection.egg-info/requires.txt
labelDetection.egg-info/top_level.txt
